ubgrade/__init__.py
ubgrade/assemble_graded_tools.py
ubgrade/email_tools.py
ubgrade/exam_code.py
ubgrade/exam_template.tex
ubgrade/grading_base.py
ubgrade/helpers.py
ubgrade/make_exams_tools.py
ubgrade/prepare_grading_tools.py
ubgrade/read_scores_tools.py
ubgrade/ubgrade.py
ubgrade/wrappers.py
ubgrade-0.1.3.dist-info/LICENSE
ubgrade-0.1.3.dist-info/METADATA
ubgrade-0.1.3.dist-info/WHEEL
ubgrade-0.1.3.dist-info/top_level.txt
ubgrade-0.1.3.dist-info/RECORD
