Metadata-Version: 2.1
Name: ubgrade
Version: 0.1.3
Summary: Automates some tasks related to preparation and grading of exams.
Home-page: https://github.com/bbadzioch/ubgrade
Author: Bernard Badzioch
Author-email: bernard.badzioch@gmail.com
License: GPLv3
Platform: UNKNOWN
Classifier: Development Status :: 3 - Alpha
Classifier: License :: OSI Approved :: GNU General Public License v3 (GPLv3)
Classifier: Programming Language :: Python :: 3
Classifier: Programming Language :: Python :: 3.7
Classifier: Operating System :: OS Independent
Classifier: Topic :: Software Development :: Libraries :: Python Modules
Requires-Dist: pdf2image
Requires-Dist: reportlab
Requires-Dist: PyPDF2
Requires-Dist: pyzbar
Requires-Dist: numpy
Requires-Dist: matplotlib
Requires-Dist: pandas
Requires-Dist: opencv-python
